{
  "generatedAt": "2026-02-07T20:43:51.461396+00:00",
  "repos": [
    {
      "fullName": "radaiko/Graft",
      "name": "Graft",
      "owner": "radaiko",
      "isOwn": true,
      "commits": 58,
      "lastActivity": "2026-02-07T20:15:16Z"
    },
    {
      "fullName": "radaiko/radaiko.github.io",
      "name": "radaiko.github.io",
      "owner": "radaiko",
      "isOwn": true,
      "commits": 1,
      "lastActivity": "2026-02-07T20:35:43Z"
    }
  ],
  "weeklyCommits": [
    0,
    0,
    0,
    0,
    0,
    0,
    0,
    0,
    0,
    0,
    0,
    59
  ],
  "totalCommits": 59,
  "activeWeeks": 1,
  "pages": [
    {
      "name": "Graft",
      "url": "https://radaiko.github.io/Graft/",
      "description": "A CLI tool for managing stacked branches and git worktrees",
      "language": "C#"
    }
  ]
}